LICENSE.txt
MANIFEST.in
README
setup.py
Wallace.egg-info/PKG-INFO
Wallace.egg-info/SOURCES.txt
Wallace.egg-info/dependency_links.txt
Wallace.egg-info/requires.txt
Wallace.egg-info/top_level.txt
wallace/__init__.py
wallace/errors.py
wallace/config/__init__.py
wallace/config/app.py
wallace/config/cache.py
wallace/config/getters.py
wallace/db/__init__.py
wallace/db/base/__init__.py
wallace/db/base/middleware.py
wallace/db/base/model.py
wallace/db/base/attrs/__init__.py
wallace/db/base/attrs/base.py
wallace/db/base/attrs/datatypes.py
wallace/db/base/attrs/interface.py
wallace/db/base/attrs/utils.py
wallace/db/base/nosql/__init__.py
wallace/db/base/nosql/model.py
wallace/db/base/sql/__init__.py
wallace/db/base/sql/model.py
wallace/db/base/sql/table.py
wallace/db/base/sql/writer.py
wallace/db/mongo/__init__.py
wallace/db/mongo/collection.py
wallace/db/mongo/document.py
wallace/db/mongo/pool.py
wallace/db/pg/__init__.py
wallace/db/pg/model.py
wallace/db/pg/pool.py
wallace/db/pg/table.py
wallace/db/redisdb/__init__.py
wallace/db/redisdb/expiring.py
wallace/db/redisdb/hash.py
wallace/db/redisdb/middleware.py
wallace/db/redisdb/sock.py